Metadata-Version: 1.0
Name: pyGeoMagApex
Version: 0.1.0
Summary: Coordination transform between GeoGraphic and GeoMagnetic
Home-page: https://github.com/zzyztyy/pyGeoMagnetic
Author: zzyztyy
Author-email: 2375672032@qq.com
License: MIT
Platform: UNKNOWN
